mycalc/calculartor.py
mycalc/setup.py
doro0001-0.0.1.dist-info/METADATA
doro0001-0.0.1.dist-info/WHEEL
doro0001-0.0.1.dist-info/top_level.txt
doro0001-0.0.1.dist-info/RECORD
