Metadata-Version: 2.1
Name: doro0001
Version: 0.0.1
Summary: nice calculartor
Home-page: https://github.com/dongkyu20/doro0001
Download-URL: https://github.com/dongkyu20/doro0001/blob/main/mycalc.py
Author: doro
License: UNKNOWN
Platform: UNKNOWN
Classifier: Programming Language :: Python :: 3
